README.rst
setup.py
django_secureliveservertestcase.egg-info/PKG-INFO
django_secureliveservertestcase.egg-info/SOURCES.txt
django_secureliveservertestcase.egg-info/dependency_links.txt
django_secureliveservertestcase.egg-info/requires.txt
django_secureliveservertestcase.egg-info/top_level.txt
secureliveservertestcase/__init__.py
secureliveservertestcase/test/__init__.py
secureliveservertestcase/test/testcases.py