Metadata-Version: 1.0
Name: django-secureliveservertestcase
Version: 0.2
Summary: Adds a SSL server for testing in Django
Home-page: http://github.com/pbrooks/django-secureliveservertestcase
Author: Peter Brooks
Author-email: spamme@pbrooks.net
License: MIT
Platform: UNKNOWN
